zta_devtools/__init__.py
zta_devtools/__main__.py
zta_devtools/cli.py
zta_devtools/docs_generator.py
zta_devtools/helpers.py
zta_devtools/info.py
zta_devtools/project_scan.py
zta_devtools/requirements.py
zta_devtools/scripts.py
zta_devtools/utils.py
zta_devtools/venv_utils.py
zta_devtools/watcher.py
zta_devtools-0.5.0.dist-info/METADATA
zta_devtools-0.5.0.dist-info/WHEEL
zta_devtools-0.5.0.dist-info/entry_points.txt
zta_devtools-0.5.0.dist-info/top_level.txt
zta_devtools-0.5.0.dist-info/RECORD
