Metadata-Version: 2.4
Name: zta-devtools
Version: 0.5.0
Summary: A developer CLI tool for Python package management, virtualenvs, scanning, and automation.
Home-page: https://github.com/ZtaMDev/zta-devtools
Author: ZtaMDev
Author-email: ZtaMDev <manuelitoricardo3@gmail.com>
License: MIT
Requires-Python: >=3.7
Requires-Dist: rich
Requires-Dist: watchdog
Requires-Dist: safety
Dynamic: author
Dynamic: home-page
Dynamic: requires-python
